{"cameraMode":{"drawMode":0,"name":"Shaded","section":"Shading Mode"},"sceneLighting":true,"audioPlay":false,"sceneViewState":{"m_AlwaysRefresh":false,"showFog":true,"showSkybox":true,"showFlares":true,"showImageEffects":true,"showParticleSystems":true,"showVisualEffectGraphs":true,"m_FxEnabled":true},"in2DMode":false,"pivot":{"x":0.7861244678497315,"y":-2.4717068672180177,"z":-4.661528587341309},"rotation":{"x":-0.3477165102958679,"y":0.40646934509277346,"z":-0.17080485820770265,"w":-0.8274756669998169},"size":9.476363182067871,"orthographic":false}